wechatpy/__init__.py
wechatpy/client/__init__.py
wechatpy/client/async/__init__.py
wechatpy/client/async/tornado.py
wechatpy_tornado/__init__.py
wechatpy_tornado/client.py
wechatpy_tornado-1.0.0.dist-info/DESCRIPTION.rst
wechatpy_tornado-1.0.0.dist-info/METADATA
wechatpy_tornado-1.0.0.dist-info/RECORD
wechatpy_tornado-1.0.0.dist-info/WHEEL
wechatpy_tornado-1.0.0.dist-info/metadata.json
wechatpy_tornado-1.0.0.dist-info/top_level.txt
